backports/__init__.py
backports/entry_points_selectable.py
backports.entry_points_selectable-1.3.0.dist-info/LICENSE
backports.entry_points_selectable-1.3.0.dist-info/METADATA
backports.entry_points_selectable-1.3.0.dist-info/WHEEL
backports.entry_points_selectable-1.3.0.dist-info/top_level.txt
backports.entry_points_selectable-1.3.0.dist-info/RECORD
